flask_bootstrapper/__init__.py
flask_bootstrapper/conf.py
flask_bootstrapper/flask_bootstrapper.py
flask_bootstrapper/bin/flask-bootstrapper.py
flask_bootstrapper-0.0.1.data/scripts/flask-bootstrapper.py
flask_bootstrapper-0.0.1.dist-info/LICENCE.txt
flask_bootstrapper-0.0.1.dist-info/METADATA
flask_bootstrapper-0.0.1.dist-info/WHEEL
flask_bootstrapper-0.0.1.dist-info/top_level.txt
flask_bootstrapper-0.0.1.dist-info/RECORD
