Metadata-Version: 2.1
Name: flask-bootstrapper
Version: 0.0.1
Summary: A simple bootstrapper for flask applications
Home-page: http://github.com/contraslash/flask-bootstrapper
Author: contraslash S.A.S.
Author-email: ma0@contraslash.com
License: MIT
Project-URL: Bug Reports, https://github.com/contraslash/flask-bootstrapper/issues
Project-URL: Source, https://github.com/contraslash/flask-bootstrapper
Project-URL: Contraslash, https://contraslash.com/
Keywords: flask bootstrapping tool
Platform: UNKNOWN
Classifier: Development Status :: 3 - Alpha
Classifier: Intended Audience :: Developers
Classifier: License :: OSI Approved :: MIT License
Classifier: Programming Language :: Python :: 3
Requires-Dist: gitpython (>=2.1)
Requires-Dist: django-crud-generator
